{
    "nodes": [
        {
            "name": "C1"
        },
        {
            "name": "A2"
        },
        {
            "name": "C3"
        },
        {
            "name": "D1"
        },
        {
            "name": "E2"
        },
        {
            "name": "A3"
        },
        {
            "name": "F4"
        },
        {
            "name": "A1"
        },
        {
            "name": "B2"
        },
        {
            "name": "C3"
        },
        {
            "name": "D4"
        },
        {
            "name": "E5"
        },
        {
            "name": "F6"
        },
        {
            "name": "C1"
        },
        {
            "name": "A2"
        },
        {
            "name": "B3"
        },
        {
            "name": "D1"
        },
        {
            "name": "E2"
        },
        {
            "name": "A3"
        },
        {
            "name": "F4"
        },
        {
            "name": "A1"
        },
        {
            "name": "B2"
        },
        {
            "name": "C3"
        },
        {
            "name": "D4"
        },
        {
            "name": "E5"
        },
        {
            "name": "F6"
        },
        {
            "name": "A1"
        },
        {
            "name": "B2"
        },
        {
            "name": "C3"
        },
        {
            "name": "A1"
        },
        {
            "name": "B2"
        },
        {
            "name": "A1"
        },
        {
            "name": "A1"
        },
        {
            "name": "B1"
        },
        {
            "name": "A2"
        },
        {
            "name": "D3"
        },
        {
            "name": "C4"
        },
        {
            "name": "B1"
        },
        {
            "name": "D2"
        },
        {
            "name": "C3"
        },
        {
            "name": "C1"
        },
        {
            "name": "D2"
        },
        {
            "name": "A3"
        },
        {
            "name": "C1"
        },
        {
            "name": "D2"
        },
        {
            "name": "B3"
        },
        {
            "name": "E4"
        },
        {
            "name": "F5"
        },
        {
            "name": "C1"
        },
        {
            "name": "A2"
        },
        {
            "name": "B3"
        }
    ],
    "links": [
        {
            "source": "Start",
            "target": "C1",
            "value": "5"
        },
        {
            "source": "C1",
            "target": "A2",
            "value": "4"
        },
        {
            "source": "A2",
            "target": "C3",
            "value": "5"
        },
        {
            "source": "Start",
            "target": "D1",
            "value": "2"
        },
        {
            "source": "D1",
            "target": "E2",
            "value": "2"
        },
        {
            "source": "E2",
            "target": "A3",
            "value": "3"
        },
        {
            "source": "A3",
            "target": "F4",
            "value": "2"
        },
        {
            "source": "Start",
            "target": "A1",
            "value": "6"
        },
        {
            "source": "A1",
            "target": "B2",
            "value": "4"
        },
        {
            "source": "B2",
            "target": "C3",
            "value": "5"
        },
        {
            "source": "C3",
            "target": "D4",
            "value": "2"
        },
        {
            "source": "D4",
            "target": "E5",
            "value": "2"
        },
        {
            "source": "E5",
            "target": "F6",
            "value": "2"
        },
        {
            "source": "Start",
            "target": "C1",
            "value": "5"
        },
        {
            "source": "C1",
            "target": "A2",
            "value": "4"
        },
        {
            "source": "A2",
            "target": "B3",
            "value": "3"
        },
        {
            "source": "Start",
            "target": "D1",
            "value": "2"
        },
        {
            "source": "D1",
            "target": "E2",
            "value": "2"
        },
        {
            "source": "E2",
            "target": "A3",
            "value": "3"
        },
        {
            "source": "A3",
            "target": "F4",
            "value": "2"
        },
        {
            "source": "Start",
            "target": "A1",
            "value": "6"
        },
        {
            "source": "A1",
            "target": "B2",
            "value": "4"
        },
        {
            "source": "B2",
            "target": "C3",
            "value": "5"
        },
        {
            "source": "C3",
            "target": "D4",
            "value": "2"
        },
        {
            "source": "D4",
            "target": "E5",
            "value": "2"
        },
        {
            "source": "E5",
            "target": "F6",
            "value": "2"
        },
        {
            "source": "Start",
            "target": "A1",
            "value": "6"
        },
        {
            "source": "A1",
            "target": "B2",
            "value": "4"
        },
        {
            "source": "B2",
            "target": "C3",
            "value": "5"
        },
        {
            "source": "Start",
            "target": "A1",
            "value": "6"
        },
        {
            "source": "A1",
            "target": "B2",
            "value": "4"
        },
        {
            "source": "Start",
            "target": "A1",
            "value": "6"
        },
        {
            "source": "Start",
            "target": "A1",
            "value": "6"
        },
        {
            "source": "Start",
            "target": "B1",
            "value": "2"
        },
        {
            "source": "B1",
            "target": "A2",
            "value": "4"
        },
        {
            "source": "A2",
            "target": "D3",
            "value": "1"
        },
        {
            "source": "D3",
            "target": "C4",
            "value": "1"
        },
        {
            "source": "Start",
            "target": "B1",
            "value": "2"
        },
        {
            "source": "B1",
            "target": "D2",
            "value": "3"
        },
        {
            "source": "D2",
            "target": "C3",
            "value": "5"
        },
        {
            "source": "Start",
            "target": "C1",
            "value": "5"
        },
        {
            "source": "C1",
            "target": "D2",
            "value": "3"
        },
        {
            "source": "D2",
            "target": "A3",
            "value": "3"
        },
        {
            "source": "Start",
            "target": "C1",
            "value": "5"
        },
        {
            "source": "C1",
            "target": "D2",
            "value": "3"
        },
        {
            "source": "D2",
            "target": "B3",
            "value": "3"
        },
        {
            "source": "B3",
            "target": "E4",
            "value": "1"
        },
        {
            "source": "E4",
            "target": "F5",
            "value": "1"
        },
        {
            "source": "Start",
            "target": "C1",
            "value": "5"
        },
        {
            "source": "C1",
            "target": "A2",
            "value": "4"
        },
        {
            "source": "A2",
            "target": "B3",
            "value": "3"
        }
    ]
}